{"doc_id": "aHR0cHM6Ly93d3cudmlsbGUtZm9zc2VzOTUuZnIvc2l0ZXMvZGVmYXVsdC9maWxlcy9hdG9tcy9maWxlcy9hbV9kMTQtMDQ0X3N0YXRpb25uZW1lbnRfem9uZV9ibGV1ZV8yNzUzLnBkZg==", "locations": [{"name": "ville-fosses95", "uid": "FRCOMM01250", "url": "https://www.ville-fosses95.fr"}], "origin_url": "https://www.ville-fosses95.fr/sites/default/files/atoms/files/am_d14-044_stationnement_zone_bleue_2753.pdf", "text": " \n \n       \n \n \n \n     \n \nARRETE MUNICIPAL PERMANENT MODIFIANT LE STATIONNEMENT EN ZONE BLEUE \n \nLe maire de FOSSES, \nVu le Code G\u00e9n\u00e9ral des Collectivit\u00e9s Territoriales, notamment les articles L. 2213-1 \u00e0 5 ; \nVu le Code de la Route notamment les articles, R. 110-1, R. 110-2, R. 411-2 \u00e0 -4, R. 411-8, R. 411-25, R. 411-26, R. 411-28, R. 414-\n14, R. 417-1 \u00e0 R. 417.13 ; \nVu le code p\u00e9nal, notamment l\u2019article R  610-5 ; \nVu l\u2019arr\u00eat\u00e9 du 24 novembre 1967 modifi\u00e9 relatif \u00e0 la signalisation des routes et des autoroutes ; \nVu l\u2019Arr\u00eat\u00e9 Minist\u00e9riel du 6 d\u00e9cembre 2007 relatif au mod\u00e8le type de dispositif de contr\u00f4le de la dur\u00e9e du stationnement urbain ; \nVu l\u2019instruction interminist\u00e9rielle sur la signalisation routi\u00e8re du 13 ao\u00fbt 1977 modifi\u00e9e ; \nVu la d\u00e9lib\u00e9ration du Conseil Municipal du 18 janvier 2012, portant r\u00e8glement du fonctionnement des cartes riverains dans les zones \u00e0 \nstationnements r\u00e9glement\u00e9s ; \nVu l\u2019Arr\u00eat\u00e9 Municipal N\u00b0D13/186 modifiant le stationnement en zone bleue du 25 novembre 2013 ; \nVu le R\u00e8glement de fonctionnement des cartes riverains ; \nConsid\u00e9rant les difficult\u00e9s des riverains \u00e0 stationner devant leur propri\u00e9t\u00e9 ou d\u2019y acc\u00e9der ; \nConsid\u00e9rant la n\u00e9cessit\u00e9 de maintenir des places de stationnement pour la client\u00e8le des commer\u00e7ants et faciliter l\u2019accessibilit\u00e9 au centre-\nVille ;  \nConsid\u00e9rant l\u2019\u00e9volution des travaux de renouvellement urbain et la g\u00eane occasionn\u00e9e ; \nConsid\u00e9rant qu\u2019il est n\u00e9cessaire de r\u00e9glementer le stationnement ; \nConsid\u00e9rant qu\u2019il est n\u00e9cessaire d\u2019adapter le stationnement dans certains cas lorsque la r\u00e9glementation actuelle s\u2019av\u00e8re inadapt\u00e9e ;  \nARRETE N\u00b0 D 14/044 \nArticle 1 : Est abrog\u00e9 l\u2019arr\u00eat\u00e9 N\u00b0 D13/186 du 25 novembre 2013 instituant le stationnement en zone bleue sur la commune. Une place \nde stationnement est supprim\u00e9e devant le 12 avenue de la Haute Gr\u00e8ve, afin de cr\u00e9er un passage pi\u00e9ton. \nArticle 2 : La dur\u00e9e du stationnement est autoris\u00e9e du lundi au vendredi de 9h00 \u00e0 12h00 et de 14h00 \u00e0 19h00, pour une dur\u00e9e ne \npouvant exc\u00e9der 1h30, except\u00e9 sur les parkings en d\u00e9pose minute des \u00e9coles Alphonse Daudet et Fr\u00e9deric Mistral, par un disque \nhomologu\u00e9 qui doit \u00eatre appos\u00e9 obligatoirement de mani\u00e8re visible \u00e0 l\u2019avant du v\u00e9hicule et conforme au mod\u00e8le de disque europ\u00e9en \ndepuis le 1er janvier 2012 sur l\u2019ensemble de la commune.   \n \nArticle 3 : Sur les parkings en d\u00e9pose-minute de l\u2019\u00e9cole Alphonse Daudet (Avenue de la Haute Gr\u00e8ve) et de l\u2019\u00e9cole Fr\u00e9d\u00e9ric Mistral \n(Avenue Liszt), le stationnement est autoris\u00e9 les lundi, mardi, jeudi et vendredi, de 7h00 \u00e0 19h00 sans interruption pour une dur\u00e9e ne \npouvant exc\u00e9der 30 minutes par un disque homologu\u00e9 qui doit \u00eatre appos\u00e9 obligatoirement de mani\u00e8re visible \u00e0 l\u2019avant du v\u00e9hicule et \nconforme au mod\u00e8le de disque europ\u00e9en depuis le 1er janvier 2012 sur l\u2019ensemble de la commune.   \n \nArticle 4 : En dehors des horaires d\u00e9finis dans le pr\u00e9sent arr\u00eat\u00e9 pour les Zones Bleues, le stationnement est libre. Pendant les p\u00e9riodes \nde vacances scolaires dont les dates sont d\u00e9finies par le Minist\u00e8re de l\u2019Education Nationale, le stationnement est libre, en dehors de la \nr\u00e8glementation d\u00e9finie par l\u2019article 2. \n \nArticle 5 : Le stationnement en zone bleue est r\u00e9glement\u00e9 sur les voies suivantes : \n \nRue C\u00e9sar Franck du num\u00e9ro 1 au num\u00e9ro 28 ; \nRue Pierre Brossolette du num\u00e9ro 2 au num\u00e9ro 36 ; \nRue Guy Mocquet du num\u00e9ro 1 au num\u00e9ro 7 ; \nRue Paul Vaillant Couturier du num\u00e9ro 6 au num\u00e9ro 29 ; \nPlace de la Libert\u00e9 du num\u00e9ro 6 au num\u00e9ro 16 ; \nRue Cugnot du num\u00e9ro 9 jusqu\u2019\u00e0 l\u2019angle de l\u2019All\u00e9e Jouffroy d\u2019Abbans ; \nAvenue Henri Barbusse c\u00f4t\u00e9 pair du num\u00e9ro 2 bis au num\u00e9ro 24 ; \nAvenue Henri Barbusse c\u00f4t\u00e9 impair de la Place Denis Papin au num\u00e9ro 27 ; \nAvenue de la Haute-Gr\u00e8ve de l\u2019intersection form\u00e9e avec la Place du 19 Mars 1962 au N\u00b012, des 2 c\u00f4t\u00e9s de la voie ; \nPlace du 19 mars 1962, Parvis de l\u2019H\u00f4tel de Ville ; \nPlace du 19 mars 1962, Centre Commercial du Plateau ; \n \n \n \nVILLE DE FOSSES \nActe certifi\u00e9 ex\u00e9cutoire apr\u00e8s avoir \u00e9t\u00e9 \ntransmis au repr\u00e9sentant de l\u2019\u00e9tat le : \n \nPubli\u00e9 le : \n \nNotifi\u00e9 le : \n \nLe Maire, Pierre BARROS \n \n \n \n \n     \n \n \n \n \n\n \n \n \n \n \n \n \nPlace du 19 mars 1962, parking du Centre commercial du Plateau (nouveau parking + extension); \nPlace du 19 mars 1962, des 2 C\u00f4t\u00e9s de la voie (anciennement Avenue de la Haute Gr\u00e8ve) ; \nRue Patrick Ventribout ; \nAvenue du Large du c\u00f4t\u00e9 des num\u00e9ros impairs entre la rue du Hunier et le cand\u00e9labre n\u00b035B04 ;  \nAvenue de la Haute-Gr\u00e8ve parking \u00e9cole Alphonse Daudet ; \nAvenue Liszt, parking \u00e9cole Fr\u00e9d\u00e9ric Mistral. \n \nArticle 6 : Le stationnement altern\u00e9 reste en vigueur sur les voies concern\u00e9es except\u00e9es : \n \nPlace de la Libert\u00e9 du num\u00e9ro 6 au num\u00e9ro 16 ; \nPlace Jean Moulin ; \nRue Cugnot du num\u00e9ro 9 jusqu\u2019\u00e0 l\u2019angle de l\u2019All\u00e9e Jouffroy d\u2019Abbans ; \nAvenue Henri Barbusse du num\u00e9ro 2bis au num\u00e9ro 27 ; \nAvenue Henri Barbusse c\u00f4t\u00e9 impair de la Place Denis Papin au num\u00e9ro 27  \nAvenue de la Haute-Gr\u00e8ve de l\u2019intersection form\u00e9e Place du 19 Mars 1962 au N\u00b012, des 2 c\u00f4t\u00e9s de la voie ; \nPlace du 19 mars 1962 ; \nRue Patrick Ventribout ;  \nAvenue du Large du c\u00f4t\u00e9 des num\u00e9ros impairs de la rue du Hunier au cand\u00e9labre n\u00b035B04 ;  \nAvenue de la Haute-Gr\u00e8ve parking \u00e9cole Alphonse Daudet ; \nAvenue Liszt, parking \u00e9cole Fr\u00e9d\u00e9ric Mistral. \n \nArticle 7 : En raison du caract\u00e8re r\u00e9sidentiel de certaines rues, une d\u00e9rogation est accord\u00e9e aux riverains. Elle est d\u00e9livr\u00e9e sous la forme \nd\u2019un justificatif conforme au r\u00e8glement de cartes riverains du 28/02/2012 d\u00e9finit par la ville de Fosses.  \n \nArticle 8 : L\u2019apposition et l\u2019utilisation de cette carte doivent \u00eatre conformes \u00e0 ce r\u00e8glement. \n \nArticle 9 : Tout autre stationnement sur ces zones de stationnement en dehors des emplacements am\u00e9nag\u00e9s est interdit et consid\u00e9r\u00e9 \ncomme g\u00eanant pendant le fonctionnement de la zone bleue. \n \nArticle 10 : La signalisation r\u00e9glementaire sera mise en place. \n \nArticle 11 : Les infractions aux dispositions du pr\u00e9sent arr\u00eat\u00e9 seront constat\u00e9es par proc\u00e8s-verbaux et poursuivies conform\u00e9ment \u00e0 la \nloi. \nArticle 12 : Le pr\u00e9sent arr\u00eat\u00e9 sera publi\u00e9 et affich\u00e9 dans la commune et ampliation sera transmise \u00e0 : \n- \nMadame le Commandant de la Brigade de Gendarmerie de FOSSES ; \n- \nAux Sapeurs Pompiers de SURVILLIERS ; \n- \nAux Services Techniques ; \n- \nAu Service Juridique ; \n- \nAux archives de la Police Municipale. \n \n \n \n \n \n \n                                                                                                                                 Fait \u00e0 Fosses, le 28 f\u00e9vrier 2014 \n                                                                                        \n \n \n \n \n \n \n   Le Maire, \n \n \n \n \n \n \n \n                                   Pierre BARROS \n \n \n \n \n \n \nLe pr\u00e9sent arr\u00eat\u00e9 pourra faire l\u2019objet d\u2019un recours contentieux form\u00e9 aupr\u00e8s du Tribunal Administratif de CERGY PONTOISE dans un d\u00e9lai de 2 mois \u00e0 \ncompter de sa publication. Il peut \u00e9galement dans le m\u00eame d\u00e9lai faire l\u2019objet d\u2019un recours gracieux intent\u00e9 devant son auteur \u00bb. \n", "publication_date": "20/12/2022"}