{"doc_id": "aHR0cDovL3d3dy5taXJpYmVsLmZyL3RlbGVjaGFyZ2VtZW50cy92aWUtbXVuaWNpcGFsZS8xNTY0LWxpc3RlLWRlcy1tYXJjaGVzLXB1YmxpY3MtMjAxNw==", "locations": [{"name": "Miribel", "uid": "FRCOMM01249", "url": "http://www.miribel.fr"}], "origin_url": "https://www.miribel.fr/telechargements/vie-municipale/1564-liste-des-marches-publics-2017/file", "text": "LISTE DES MARCHES PUBLICS 2017\nN\u00b0 de march\u00e9\nmode de passation\nobjet du march\u00e9\ndate de notification\nmontant, HT\nAttributaire\ncode postal de \nl'Attributaire\n17.004\nMAPA\nPRESTATIONS D'INFOGERANCE MAIRIE ET ECOLES ET \nFOURNITURE D'EQUIPEMENT INFORMATIQUE SERVICE \nD'HEBERGEMENT\n21/04/2017\nMARCHE A BON DE \nCOMMANDES SANS MINIUM \nSANS MAXIMUM\nSARL ONE SYSTEM\n01 700\n17.006\nMAPA\nFOURNITURE DE REPAS EN LIAISON FROIDE POUR LES \nBESOINS DE LA COMMUNE DE MIIRBEL\n28/08/2017\nMINI 270 000 \u20ac\nMAXI 420 000 \u20ac\nSAS ELRES\n92 032\n16.010\nMAPA\nEXTENSION E QUINET CREATION D UNE NOUVELLE CANTINE \nLOT 7\n18/01/2017\n60 510,00 \u20ac\nETS DUMAN\n69 780\n16.010\nMAPA\nEXTENSION E QUINET CREATION D UNE NOUVELLE CANTINE \nLOT 11\n17/01/2017\n31 354,57 \u20ac\nETS GUILLOT\n01 120\n16.010\nMAPA\nEXTENSION E QUINET CREATION D UNE NOUVELLE CANTINE \nLOT 12\n17/01/2017\n112 275,73 \u20ac\nETS CANO\n69 200\n16.010\nMAPA\nEXTENSION E QUINET CREATION D UNE NOUVELLE CANTINE \nLOT 14\n26/07/2017\n78 372,00 \u20ac\nSAS CUNY\n01 006\n17.001\nMAPA\nREFECTION TERRAIN TENNIS\n25/04/2017\n83 993,28 \u20ac\nSAS LAQUET\n26 210\n17.002\nMAPA\nASSAINISSEMENT AUX ECHETS\n10/04/2017\n689 169,06 \u20ac\nSAS BRUNET TP\n01 503\n17.007\nPROCEDURE ADAPTEE\nMISE EN SEPARATIF ASSAINISSMENT E. QUINET\n09/10/2017\n44 884,56 \u20ac\nSAS BRUNET TP\n01 503\n17.008\nMAPA\nDEMOLITION TRANSFORMATEUR EDF RUE DES ECOLES\n08/09/2017\n179 730,29 \u20ac\nSAS SLTP\n69 530\n17.009\nSUPPRIME\n17.010\nMAPA\nILOT ST ROMAIN: lot 1 DESAMIANTAGE\n27/12/2017\n83 880,00 \u20ac\nSAS SOGEA\n69 603\n17.010\nMAPA\nILOT ST ROMAIN: lot 2  DEMOLITION MACONNERIE \nETANCHEITE\nSAS TABOURET\n01 240\n \nFOURNITURES ET SERVICES SEUIL DE 209 000 \u20ac\nTRAVAUX  SEUIL DE 5 225 000 \u20ac\nPRESTATIONS INTELLECTUELLES\n\n17.011\nMAPA\nPLAN DE VALORISATION DE L ARCHITECTURE ET DU \nPATRIMOINE\n26/12/2017\n78 960,00 \u20ac\nSARL ARCHIPAT\n69 009\n17.003\nMAPA\nZAC CENTRE VILLE MISSION D'URBANISME ARCHITECTURE \nDE PAYSAGE ETUDES ENVIRONEMENTALES ET \nD'INFRASTRUCTURE\n10/04/2017\n68 801,40 \u20ac\nAgence ATELIER DU \nTRIANGE\n71 000\n17.005\nMAPA\nAMO ILOT ST ROMAIN \n10/05/2017\n118 800,00 \u20ac\nSARL CAP \nARCHITECTURE\n01 700\n", "publication_date": "20/12/2022"}